LICENSE
MANIFEST.in
README.md
changelog.md
manage.py
setup.py
celery_apps/__init__.py
celery_apps/pmworker.py
config/__init__.py
config/celery.py
config/urls.py
config/wsgi.py
config/settings/__init__.py
config/settings/base.py
config/settings/development.example.py
config/settings/devtmp.py
config/settings/test.py
papermerge/__init__.py
papermerge.egg-info/PKG-INFO
papermerge.egg-info/SOURCES.txt
papermerge.egg-info/dependency_links.txt
papermerge.egg-info/top_level.txt
papermerge/boss/__init__.py
papermerge/boss/admin.py
papermerge/boss/apps.py
papermerge/boss/forms.py
papermerge/boss/options.py
papermerge/boss/users.py
papermerge/boss/widgets.py
papermerge/boss/locale/de/LC_MESSAGES/django.mo
papermerge/boss/locale/de/LC_MESSAGES/django.po
papermerge/boss/management/__init__.py
papermerge/boss/management/commands/__init__.py
papermerge/boss/management/commands/createrootuser.py
papermerge/boss/management/commands/tenants_command.py
papermerge/boss/management/commands/thumbify.py
papermerge/boss/management/commands/thumbify/thumb.pdf
papermerge/boss/migrations/__init__.py
papermerge/boss/static/boss/css/papermerge.css
papermerge/boss/static/boss/css/papermerge.css.map
papermerge/boss/static/boss/fonts/Lato-Black.ttf
papermerge/boss/static/boss/fonts/Lato-Black.woff
papermerge/boss/static/boss/fonts/Lato-BlackItalic.ttf
papermerge/boss/static/boss/fonts/Lato-BlackItalic.woff
papermerge/boss/static/boss/fonts/Lato-Bold.ttf
papermerge/boss/static/boss/fonts/Lato-Bold.woff
papermerge/boss/static/boss/fonts/Lato-BoldItalic.ttf
papermerge/boss/static/boss/fonts/Lato-BoldItalic.woff
papermerge/boss/static/boss/fonts/Lato-Hairline.ttf
papermerge/boss/static/boss/fonts/Lato-Hairline.woff
papermerge/boss/static/boss/fonts/Lato-HairlineItalic.ttf
papermerge/boss/static/boss/fonts/Lato-HairlineItalic.woff
papermerge/boss/static/boss/fonts/Lato-Italic.ttf
papermerge/boss/static/boss/fonts/Lato-Italic.woff
papermerge/boss/static/boss/fonts/Lato-Light.ttf
papermerge/boss/static/boss/fonts/Lato-Light.woff
papermerge/boss/static/boss/fonts/Lato-LightItalic.ttf
papermerge/boss/static/boss/fonts/Lato-Regular.ttf
