Metadata-Version: 2.1
Name: papermerge
Version: 1.3.0
Summary: Open source document management system (DMS)
Home-page: https://papermerge.com/
Author: Eugen Ciur
Author-email: eugen@papermerge.com
License: Apache 2.0 License
Platform: UNKNOWN
Classifier: Programming Language :: Python :: 3
Classifier: License :: OSI Approved :: Apache Software License
Classifier: Operating System :: OS Independent
Requires-Python: >=3.8
